id_card_recognition/__init__.py
id_card_recognition/recognition.py
id_card_recognition/utils.py
id_card_recognition-0.3.9.dist-info/METADATA
id_card_recognition-0.3.9.dist-info/WHEEL
id_card_recognition-0.3.9.dist-info/entry_points.txt
id_card_recognition-0.3.9.dist-info/top_level.txt
id_card_recognition-0.3.9.dist-info/RECORD
