Metadata-Version: 2.1
Name: id_card_recognition
Version: 0.3.9
Summary: A package for ID card recognition using Moonshot AI
Home-page: 
Author: freedak Wang
Author-email: freedak@163.com
Classifier: Programming Language :: Python :: 3
Classifier: License :: OSI Approved :: MIT License
Classifier: Operating System :: OS Independent
Requires-Dist: requests
Requires-Dist: natsort
Requires-Dist: openai
Requires-Dist: python-dotenv
